pythonaem/__init__.py
pythonaem/client.py
pythonaem/error.py
pythonaem/response.py
pythonaem/result.py
pythonaem/swagger.py
pythonaem/conf/spec.yaml
pythonaem/handlers/__init__.py
pythonaem/handlers/simple.py
pythonaem/resources/__init__.py
pythonaem/resources/aem.py
pythonaem/resources/flush_agent.py
pythonaem/resources/replication_agent.py
pythonaem-1.8.1.dist-info/LICENSE
pythonaem-1.8.1.dist-info/METADATA
pythonaem-1.8.1.dist-info/WHEEL
pythonaem-1.8.1.dist-info/top_level.txt
pythonaem-1.8.1.dist-info/zip-safe
pythonaem-1.8.1.dist-info/RECORD
