Metadata-Version: 2.1
Name: pythonaem
Version: 1.8.1
Summary: Python client for AEM API
Home-page: https://github.com/shinesolutions/pythonaem
Author: Shine Solutions
Author-email: opensource@shinesolutions.com
License: UNKNOWN
Keywords: Adobe Experience Manager (AEM) API
Platform: UNKNOWN
Classifier: Programming Language :: Python :: 3
Classifier: License :: OSI Approved :: Apache Software License
Classifier: Operating System :: OS Independent
Requires-Python: >=3.6
License-File: LICENSE
Requires-Dist: pyyaml (==5.4.1)
Requires-Dist: swaggeraem (==1.2.0)
